devtrack/__init__.py
devtrack/cli.py
devtrack/commits.py
devtrack/project.py
devtrack/tasks.py
devtrack/utils.py
devtrack/scripts/generate_changelog.py
devtrack-0.1.3.dist-info/licenses/LICENSE.txt
devtrack-0.1.3.dist-info/METADATA
devtrack-0.1.3.dist-info/WHEEL
devtrack-0.1.3.dist-info/entry_points.txt
devtrack-0.1.3.dist-info/top_level.txt
devtrack-0.1.3.dist-info/RECORD
