Metadata-Version: 2.4
Name: devtrack
Version: 0.1.3
Summary: Developer task tracking and smart AI commit CLI tool
Author-email: Raymond Degbe <mrdegbe14@gmail.com>
License: MIT
Project-URL: Homepage, https://github.com/mrdegbe/devtrack
Keywords: git,commit,cli,developer,productivity,ai
Classifier: Development Status :: 3 - Alpha
Classifier: Intended Audience :: Developers
Classifier: Programming Language :: Python :: 3
Classifier: Programming Language :: Python :: 3.8
Classifier: License :: OSI Approved :: MIT License
Classifier: Operating System :: OS Independent
Requires-Python: >=3.7
License-File: LICENSE.txt
Requires-Dist: requests
Requires-Dist: python-dotenv
Requires-Dist: openai
Dynamic: license-file
